genieparse/__init__.py
genieparse/genieparse.py
genieparse-0.0.2.dist-info/LICENSE
genieparse-0.0.2.dist-info/METADATA
genieparse-0.0.2.dist-info/WHEEL
genieparse-0.0.2.dist-info/top_level.txt
genieparse-0.0.2.dist-info/RECORD
